[
  {
    "round": 1,
    "phase": 1,
    "table": null,
    "winner": -1,
    "player1": "jojojess"
  },
  {
    "round": 1,
    "phase": 1,
    "table": null,
    "winner": -1,
    "player1": "fokker111"
  },
  {
    "round": 1,
    "phase": 1,
    "table": 1,
    "winner": "tylyn",
    "player1": "m4kia_t",
    "player2": "tylyn"
  },
  {
    "round": 1,
    "phase": 1,
    "table": 2,
    "winner": "dakka_1988",
    "player1": "dakka_1988",
    "player2": "hof_khran"
  },
  {
    "round": 1,
    "phase": 1,
    "table": 3,
    "winner": "ilikecheese216",
    "player1": "shakthar",
    "player2": "ilikecheese216"
  },
  {
    "round": 1,
    "phase": 1,
    "table": 4,
    "winner": "sleepy512pete",
    "player1": "sleepy512pete",
    "player2": "ibrakadabra"
  },
  {
    "round": 1,
    "phase": 1,
    "table": 5,
    "winner": -1,
    "player1": "mibo19",
    "player2": "aegon_targaryen"
  },
  {
    "round": 1,
    "phase": 1,
    "table": 6,
    "winner": "4th_d",
    "player1": "4th_d",
    "player2": "bellins"
  },
  {
    "round": 1,
    "phase": 1,
    "table": 7,
    "winner": "blackjograce",
    "player1": "warpis",
    "player2": "blackjograce"
  },
  {
    "round": 1,
    "phase": 1,
    "table": 8,
    "winner": "raindrop2cool",
    "player1": "devastazioneh88",
    "player2": "raindrop2cool"
  },
  {
    "round": 1,
    "phase": 1,
    "table": 9,
    "winner": "neesh",
    "player1": "neesh",
    "player2": "padrepio97"
  },
  {
    "round": 1,
    "phase": 1,
    "table": 10,
    "winner": "haruhi_1350",
    "player1": "leaffff",
    "player2": "haruhi_1350"
  },
  {
    "round": 1,
    "phase": 1,
    "table": 11,
    "winner": "elliedark",
    "player1": "elliedark",
    "player2": "barloupike"
  },
  {
    "round": 1,
    "phase": 1,
    "table": 12,
    "winner": "elnari",
    "player1": "chv3173",
    "player2": "elnari"
  },
  {
    "round": 1,
    "phase": 1,
    "table": 13,
    "winner": "xctloya26",
    "player1": "xctloya26",
    "player2": "madarauchiwa"
  },
  {
    "round": 1,
    "phase": 1,
    "table": 14,
    "winner": "kk_momos",
    "player1": "javiee333",
    "player2": "kk_momos"
  },
  {
    "round": 1,
    "phase": 1,
    "table": 15,
    "winner": "supreme13",
    "player1": "supreme13",
    "player2": "bath01"
  },
  {
    "round": 2,
    "phase": 1,
    "table": 1,
    "winner": "dakka_1988",
    "player1": "dakka_1988",
    "player2": "blackjograce"
  },
  {
    "round": 2,
    "phase": 1,
    "table": 2,
    "winner": "xctloya26",
    "player1": "xctloya26",
    "player2": "neesh"
  },
  {
    "round": 2,
    "phase": 1,
    "table": 3,
    "winner": "supreme13",
    "player1": "supreme13",
    "player2": "haruhi_1350"
  },
  {
    "round": 2,
    "phase": 1,
    "table": 4,
    "winner": "ilikecheese216",
    "player1": "4th_d",
    "player2": "ilikecheese216"
  },
  {
    "round": 2,
    "phase": 1,
    "table": 5,
    "winner": "tylyn",
    "player1": "sleepy512pete",
    "player2": "tylyn"
  },
  {
    "round": 2,
    "phase": 1,
    "table": 6,
    "winner": "raindrop2cool",
    "player1": "kk_momos",
    "player2": "raindrop2cool"
  },
  {
    "round": 2,
    "phase": 1,
    "table": 7,
    "winner": "elnari",
    "player1": "elnari",
    "player2": "elliedark"
  },
  {
    "round": 2,
    "phase": 1,
    "table": 8,
    "winner": "devastazioneh88",
    "player1": "leaffff",
    "player2": "devastazioneh88"
  },
  {
    "round": 2,
    "phase": 1,
    "table": 9,
    "winner": "jojojess",
    "player1": "jojojess",
    "player2": "chv3173"
  },
  {
    "round": 2,
    "phase": 1,
    "table": 10,
    "winner": "ibrakadabra",
    "player1": "ibrakadabra",
    "player2": "javiee333"
  },
  {
    "round": 2,
    "phase": 1,
    "table": 11,
    "winner": "m4kia_t",
    "player1": "m4kia_t",
    "player2": "warpis"
  },
  {
    "round": 3,
    "phase": 1,
    "table": 1,
    "winner": "dakka_1988",
    "player1": "elnari",
    "player2": "dakka_1988"
  },
  {
    "round": 3,
    "phase": 1,
    "table": 2,
    "winner": "ilikecheese216",
    "player1": "tylyn",
    "player2": "ilikecheese216"
  },
  {
    "round": 3,
    "phase": 1,
    "table": 3,
    "winner": "supreme13",
    "player1": "supreme13",
    "player2": "xctloya26"
  },
  {
    "round": 3,
    "phase": 1,
    "table": 4,
    "winner": "m4kia_t",
    "player1": "raindrop2cool",
    "player2": "m4kia_t"
  },
  {
    "round": 3,
    "phase": 1,
    "table": 5,
    "winner": "sleepy512pete",
    "player1": "sleepy512pete",
    "player2": "jojojess"
  },
  {
    "round": 3,
    "phase": 1,
    "table": 6,
    "winner": "devastazioneh88",
    "player1": "devastazioneh88",
    "player2": "blackjograce"
  },
  {
    "round": 3,
    "phase": 1,
    "table": 7,
    "winner": "kk_momos",
    "player1": "kk_momos",
    "player2": "neesh"
  },
  {
    "round": 3,
    "phase": 1,
    "table": 8,
    "winner": "ibrakadabra",
    "player1": "4th_d",
    "player2": "ibrakadabra"
  },
  {
    "round": 3,
    "phase": 1,
    "table": 9,
    "winner": "haruhi_1350",
    "player1": "elliedark",
    "player2": "haruhi_1350"
  },
  {
    "round": 3,
    "phase": 1,
    "table": 10,
    "winner": "javiee333",
    "player1": "javiee333",
    "player2": "chv3173"
  },
  {
    "round": 3,
    "phase": 1,
    "table": 11,
    "winner": "leaffff",
    "player1": "leaffff"
  },
  {
    "round": 4,
    "phase": 1,
    "table": 1,
    "winner": "ilikecheese216",
    "player1": "ilikecheese216",
    "player2": "supreme13"
  },
  {
    "round": 4,
    "phase": 1,
    "table": 2,
    "winner": "dakka_1988",
    "player1": "dakka_1988",
    "player2": "sleepy512pete"
  },
  {
    "round": 4,
    "phase": 1,
    "table": 3,
    "winner": "elnari",
    "player1": "raindrop2cool",
    "player2": "elnari"
  },
  {
    "round": 4,
    "phase": 1,
    "table": 4,
    "winner": "m4kia_t",
    "player1": "m4kia_t",
    "player2": "kk_momos"
  },
  {
    "round": 4,
    "phase": 1,
    "table": 5,
    "winner": "haruhi_1350",
    "player1": "haruhi_1350",
    "player2": "ibrakadabra"
  },
  {
    "round": 4,
    "phase": 1,
    "table": 6,
    "winner": "xctloya26",
    "player1": "xctloya26",
    "player2": "devastazioneh88"
  },
  {
    "round": 4,
    "phase": 1,
    "table": 7,
    "winner": "tylyn",
    "player1": "tylyn",
    "player2": "blackjograce"
  },
  {
    "round": 4,
    "phase": 1,
    "table": 8,
    "winner": "4th_d",
    "player1": "4th_d",
    "player2": "jojojess"
  },
  {
    "round": 4,
    "phase": 1,
    "table": 9,
    "winner": "javiee333",
    "player1": "javiee333",
    "player2": "neesh"
  },
  {
    "round": 4,
    "phase": 1,
    "table": 10,
    "winner": "elliedark",
    "player1": "leaffff",
    "player2": "elliedark"
  },
  {
    "round": 5,
    "phase": 1,
    "table": 1,
    "winner": "dakka_1988",
    "player1": "ilikecheese216",
    "player2": "dakka_1988"
  },
  {
    "round": 5,
    "phase": 1,
    "table": 2,
    "winner": "supreme13",
    "player1": "supreme13",
    "player2": "tylyn"
  },
  {
    "round": 5,
    "phase": 1,
    "table": 3,
    "winner": "haruhi_1350",
    "player1": "haruhi_1350",
    "player2": "elnari"
  },
  {
    "round": 5,
    "phase": 1,
    "table": 4,
    "winner": "xctloya26",
    "player1": "xctloya26",
    "player2": "m4kia_t"
  },
  {
    "round": 5,
    "phase": 1,
    "table": 5,
    "winner": "devastazioneh88",
    "player1": "devastazioneh88",
    "player2": "javiee333"
  },
  {
    "round": 5,
    "phase": 1,
    "table": 6,
    "winner": "ibrakadabra",
    "player1": "ibrakadabra",
    "player2": "elliedark"
  },
  {
    "round": 5,
    "phase": 1,
    "table": 7,
    "winner": "raindrop2cool",
    "player1": "raindrop2cool",
    "player2": "sleepy512pete"
  },
  {
    "round": 5,
    "phase": 1,
    "table": 8,
    "winner": "4th_d",
    "player1": "kk_momos",
    "player2": "4th_d"
  },
  {
    "round": 5,
    "phase": 1,
    "table": 9,
    "winner": "blackjograce",
    "player1": "blackjograce",
    "player2": "leaffff"
  },
  {
    "round": 5,
    "phase": 1,
    "table": 10,
    "winner": "jojojess",
    "player1": "jojojess",
    "player2": "neesh"
  },
  {
    "phase": 2,
    "round": 6,
    "winner": "ilikecheese216",
    "match": "T4-2",
    "player1": "tylyn",
    "player2": "ilikecheese216"
  },
  {
    "phase": 2,
    "round": 6,
    "winner": "m4kia_t",
    "match": "T16-2",
    "player1": "m4kia_t",
    "player2": "raindrop2cool"
  },
  {
    "phase": 2,
    "round": 6,
    "winner": "haruhi_1350",
    "match": "T4-1",
    "player1": "m4kia_t",
    "player2": "haruhi_1350"
  },
  {
    "phase": 2,
    "round": 6,
    "winner": "xctloya26",
    "match": "T16-4",
    "player1": "xctloya26",
    "player2": "devastazioneh88"
  },
  {
    "phase": 2,
    "round": 6,
    "winner": "dakka_1988",
    "match": "T16-1",
    "player1": "dakka_1988"
  },
  {
    "phase": 2,
    "round": 6,
    "winner": "m4kia_t",
    "match": "T8-1",
    "player1": "dakka_1988",
    "player2": "m4kia_t"
  },
  {
    "phase": 2,
    "round": 6,
    "winner": "ilikecheese216",
    "match": "T8-4",
    "player1": "ilikecheese216",
    "player2": "elnari"
  },
  {
    "phase": 2,
    "round": 6,
    "winner": "elnari",
    "match": "T16-8",
    "player1": "elnari",
    "player2": "4th_d"
  },
  {
    "phase": 2,
    "round": 6,
    "winner": "tylyn",
    "match": "T16-6",
    "player1": "tylyn",
    "player2": "ibrakadabra"
  },
  {
    "phase": 2,
    "round": 6,
    "winner": "ilikecheese216",
    "match": "T16-7",
    "player1": "ilikecheese216"
  },
  {
    "phase": 2,
    "round": 6,
    "winner": "haruhi_1350",
    "match": "T2-1",
    "player1": "haruhi_1350",
    "player2": "ilikecheese216"
  },
  {
    "phase": 2,
    "round": 6,
    "winner": "haruhi_1350",
    "match": "T8-2",
    "player1": "haruhi_1350",
    "player2": "xctloya26"
  },
  {
    "phase": 2,
    "round": 6,
    "winner": "haruhi_1350",
    "match": "T16-3",
    "player1": "haruhi_1350"
  },
  {
    "phase": 2,
    "round": 6,
    "winner": "tylyn",
    "match": "T8-3",
    "player1": "supreme13",
    "player2": "tylyn"
  },
  {
    "phase": 2,
    "round": 6,
    "winner": "supreme13",
    "match": "T16-5",
    "player1": "supreme13"
  }
]