[
  {
    "round": 1,
    "phase": 1,
    "table": null,
    "winner": -1,
    "player1": "jjet"
  },
  {
    "round": 1,
    "phase": 1,
    "table": null,
    "winner": -1,
    "player1": "flipand11"
  },
  {
    "round": 1,
    "phase": 1,
    "table": null,
    "winner": -1,
    "player1": "jayswan"
  },
  {
    "round": 1,
    "phase": 1,
    "table": null,
    "winner": -1,
    "player1": "russ_ii"
  },
  {
    "round": 1,
    "phase": 1,
    "table": null,
    "winner": -1,
    "player1": "hiii1"
  },
  {
    "round": 1,
    "phase": 1,
    "table": null,
    "winner": -1,
    "player1": "kraby29"
  },
  {
    "round": 1,
    "phase": 1,
    "table": 1,
    "winner": "jrab",
    "player1": "jrab",
    "player2": "yaboishaad"
  },
  {
    "round": 1,
    "phase": 1,
    "table": 2,
    "winner": "abbeie00",
    "player1": "masterlando_420",
    "player2": "abbeie00"
  },
  {
    "round": 1,
    "phase": 1,
    "table": 3,
    "winner": "ansito",
    "player1": "ansito",
    "player2": "shinra67"
  },
  {
    "round": 1,
    "phase": 1,
    "table": 4,
    "winner": "wall456",
    "player1": "wall456",
    "player2": "jb_ballemall007"
  },
  {
    "round": 1,
    "phase": 1,
    "table": 5,
    "winner": "r2rjp1",
    "player1": "r2rjp1",
    "player2": "killbo"
  },
  {
    "round": 1,
    "phase": 1,
    "table": 6,
    "winner": "proskiftw",
    "player1": "kiddoz",
    "player2": "proskiftw"
  },
  {
    "round": 1,
    "phase": 1,
    "table": 7,
    "winner": "ruzlv",
    "player1": "ruzlv",
    "player2": "ggreaper134"
  },
  {
    "round": 1,
    "phase": 1,
    "table": 8,
    "winner": "sas",
    "player1": "normo360",
    "player2": "sas"
  },
  {
    "round": 1,
    "phase": 1,
    "table": 9,
    "winner": "aetherbenny",
    "player1": "aetherbenny",
    "player2": "flipinton"
  },
  {
    "round": 1,
    "phase": 1,
    "table": 10,
    "winner": "noobslybot_01",
    "player1": "noobslybot_01",
    "player2": "estxkilla"
  },
  {
    "round": 1,
    "phase": 1,
    "table": 11,
    "winner": "awbscene",
    "player1": "winkpiee",
    "player2": "awbscene"
  },
  {
    "round": 1,
    "phase": 1,
    "table": 12,
    "winner": "2sick",
    "player1": "dracoz",
    "player2": "2sick"
  },
  {
    "round": 1,
    "phase": 1,
    "table": 13,
    "winner": "themagikarp",
    "player1": "fulcrumguy",
    "player2": "themagikarp"
  },
  {
    "round": 1,
    "phase": 1,
    "table": 14,
    "winner": "stachyv2",
    "player1": "finpin",
    "player2": "stachyv2"
  },
  {
    "round": 1,
    "phase": 1,
    "table": 15,
    "winner": "my",
    "player1": "tobias_oak",
    "player2": "my"
  },
  {
    "round": 1,
    "phase": 1,
    "table": 16,
    "winner": "kakashi93",
    "player1": "kakashi93",
    "player2": "arackz85"
  },
  {
    "round": 1,
    "phase": 1,
    "table": 17,
    "winner": "rossytribiani",
    "player1": "oddmami",
    "player2": "rossytribiani"
  },
  {
    "round": 1,
    "phase": 1,
    "table": 18,
    "winner": "konono",
    "player1": "adi1906",
    "player2": "konono"
  },
  {
    "round": 1,
    "phase": 1,
    "table": 19,
    "winner": "rno",
    "player1": "khronistr",
    "player2": "rno"
  },
  {
    "round": 1,
    "phase": 1,
    "table": 20,
    "winner": "disposablehero",
    "player1": "disposablehero",
    "player2": "manutan"
  },
  {
    "round": 1,
    "phase": 1,
    "table": 21,
    "winner": "javiee333",
    "player1": "gato_333",
    "player2": "javiee333"
  },
  {
    "round": 1,
    "phase": 1,
    "table": 22,
    "winner": "cyrunix",
    "player1": "cyrunix",
    "player2": "hallow"
  },
  {
    "round": 1,
    "phase": 1,
    "table": 23,
    "winner": "graywheel6210",
    "player1": "mo0nwa1k3r",
    "player2": "graywheel6210"
  },
  {
    "round": 1,
    "phase": 1,
    "table": 24,
    "winner": "mrd",
    "player1": "elliedark",
    "player2": "mrd"
  },
  {
    "round": 1,
    "phase": 1,
    "table": 25,
    "winner": "piutonium",
    "player1": "piutonium",
    "player2": "darkus96"
  },
  {
    "round": 1,
    "phase": 1,
    "table": 26,
    "winner": "alhag114",
    "player1": "alhag114",
    "player2": "iduh"
  },
  {
    "round": 1,
    "phase": 1,
    "table": 27,
    "winner": "tommyhp",
    "player1": "sheedy",
    "player2": "tommyhp"
  },
  {
    "round": 1,
    "phase": 1,
    "table": 28,
    "winner": "r0zey",
    "player1": "r0zey",
    "player2": "thay195"
  },
  {
    "round": 1,
    "phase": 1,
    "table": 29,
    "winner": "acebakun",
    "player1": "danimal",
    "player2": "acebakun"
  },
  {
    "round": 1,
    "phase": 1,
    "table": 30,
    "winner": "skl_yizzy",
    "player1": "luxmea",
    "player2": "skl_yizzy"
  },
  {
    "round": 1,
    "phase": 1,
    "table": 31,
    "winner": "joshuasutherland21",
    "player1": "joshuasutherland21",
    "player2": "akfirestorm"
  },
  {
    "round": 2,
    "phase": 1,
    "table": null,
    "winner": -1,
    "player1": "kraby29"
  },
  {
    "round": 2,
    "phase": 1,
    "table": null,
    "winner": -1,
    "player1": "flipand11"
  },
  {
    "round": 2,
    "phase": 1,
    "table": 1,
    "winner": "proskiftw",
    "player1": "proskiftw",
    "player2": "ansito"
  },
  {
    "round": 2,
    "phase": 1,
    "table": 2,
    "winner": "rossytribiani",
    "player1": "jrab",
    "player2": "rossytribiani"
  },
  {
    "round": 2,
    "phase": 1,
    "table": 3,
    "winner": "mrd",
    "player1": "mrd",
    "player2": "konono"
  },
  {
    "round": 2,
    "phase": 1,
    "table": 4,
    "winner": "cyrunix",
    "player1": "abbeie00",
    "player2": "cyrunix"
  },
  {
    "round": 2,
    "phase": 1,
    "table": 5,
    "winner": "my",
    "player1": "my",
    "player2": "alhag114"
  },
  {
    "round": 2,
    "phase": 1,
    "table": 6,
    "winner": "rno",
    "player1": "rno",
    "player2": "stachyv2"
  },
  {
    "round": 2,
    "phase": 1,
    "table": 7,
    "winner": "r0zey",
    "player1": "acebakun",
    "player2": "r0zey"
  },
  {
    "round": 2,
    "phase": 1,
    "table": 8,
    "winner": "noobslybot_01",
    "player1": "joshuasutherland21",
    "player2": "noobslybot_01"
  },
  {
    "round": 2,
    "phase": 1,
    "table": 9,
    "winner": "ruzlv",
    "player1": "ruzlv",
    "player2": "wall456"
  },
  {
    "round": 2,
    "phase": 1,
    "table": 10,
    "winner": "kakashi93",
    "player1": "graywheel6210",
    "player2": "kakashi93"
  },
  {
    "round": 2,
    "phase": 1,
    "table": 11,
    "winner": "2sick",
    "player1": "2sick",
    "player2": "sas"
  },
  {
    "round": 2,
    "phase": 1,
    "table": 12,
    "winner": "awbscene",
    "player1": "themagikarp",
    "player2": "awbscene"
  },
  {
    "round": 2,
    "phase": 1,
    "table": 13,
    "winner": "piutonium",
    "player1": "piutonium",
    "player2": "r2rjp1"
  },
  {
    "round": 2,
    "phase": 1,
    "table": 14,
    "winner": "skl_yizzy",
    "player1": "skl_yizzy",
    "player2": "javiee333"
  },
  {
    "round": 2,
    "phase": 1,
    "table": 15,
    "winner": "tommyhp",
    "player1": "aetherbenny",
    "player2": "tommyhp"
  },
  {
    "round": 2,
    "phase": 1,
    "table": 16,
    "winner": "disposablehero",
    "player1": "disposablehero",
    "player2": "iduh"
  },
  {
    "round": 2,
    "phase": 1,
    "table": 17,
    "winner": "elliedark",
    "player1": "thay195",
    "player2": "elliedark"
  },
  {
    "round": 2,
    "phase": 1,
    "table": 18,
    "winner": "fulcrumguy",
    "player1": "fulcrumguy",
    "player2": "kiddoz"
  },
  {
    "round": 2,
    "phase": 1,
    "table": 19,
    "winner": "manutan",
    "player1": "winkpiee",
    "player2": "manutan"
  },
  {
    "round": 2,
    "phase": 1,
    "table": 20,
    "winner": "darkus96",
    "player1": "darkus96",
    "player2": "finpin"
  },
  {
    "round": 2,
    "phase": 1,
    "table": 21,
    "winner": "gato_333",
    "player1": "gato_333",
    "player2": "jjet"
  },
  {
    "round": 2,
    "phase": 1,
    "table": 22,
    "winner": "khronistr",
    "player1": "khronistr",
    "player2": "jayswan"
  },
  {
    "round": 2,
    "phase": 1,
    "table": 23,
    "winner": "dracoz",
    "player1": "hallow",
    "player2": "dracoz"
  },
  {
    "round": 2,
    "phase": 1,
    "table": 24,
    "winner": "akfirestorm",
    "player1": "arackz85",
    "player2": "akfirestorm"
  },
  {
    "round": 2,
    "phase": 1,
    "table": 25,
    "winner": "sheedy",
    "player1": "normo360",
    "player2": "sheedy"
  },
  {
    "round": 2,
    "phase": 1,
    "table": 26,
    "winner": "killbo",
    "player1": "oddmami",
    "player2": "killbo"
  },
  {
    "round": 2,
    "phase": 1,
    "table": 27,
    "winner": "estxkilla",
    "player1": "estxkilla",
    "player2": "jb_ballemall007"
  },
  {
    "round": 2,
    "phase": 1,
    "table": 28,
    "winner": "russ_ii",
    "player1": "flipinton",
    "player2": "russ_ii"
  },
  {
    "round": 2,
    "phase": 1,
    "table": 29,
    "winner": "shinra67",
    "player1": "luxmea",
    "player2": "shinra67"
  },
  {
    "round": 2,
    "phase": 1,
    "table": 30,
    "winner": "tobias_oak",
    "player1": "tobias_oak",
    "player2": "hiii1"
  },
  {
    "round": 2,
    "phase": 1,
    "table": 31,
    "winner": "yaboishaad",
    "player1": "yaboishaad",
    "player2": "ggreaper134"
  },
  {
    "round": 2,
    "phase": 1,
    "table": 32,
    "winner": "mo0nwa1k3r",
    "player1": "mo0nwa1k3r"
  },
  {
    "round": 3,
    "phase": 1,
    "table": 1,
    "winner": "noobslybot_01",
    "player1": "noobslybot_01",
    "player2": "cyrunix"
  },
  {
    "round": 3,
    "phase": 1,
    "table": 2,
    "winner": "2sick",
    "player1": "2sick",
    "player2": "skl_yizzy"
  },
  {
    "round": 3,
    "phase": 1,
    "table": 3,
    "winner": "disposablehero",
    "player1": "disposablehero",
    "player2": "rossytribiani"
  },
  {
    "round": 3,
    "phase": 1,
    "table": 4,
    "winner": "my",
    "player1": "kakashi93",
    "player2": "my"
  },
  {
    "round": 3,
    "phase": 1,
    "table": 5,
    "winner": "r0zey",
    "player1": "ruzlv",
    "player2": "r0zey"
  },
  {
    "round": 3,
    "phase": 1,
    "table": 6,
    "winner": "awbscene",
    "player1": "rno",
    "player2": "awbscene"
  },
  {
    "round": 3,
    "phase": 1,
    "table": 7,
    "winner": "piutonium",
    "player1": "piutonium",
    "player2": "mrd"
  },
  {
    "round": 3,
    "phase": 1,
    "table": 8,
    "winner": "proskiftw",
    "player1": "tommyhp",
    "player2": "proskiftw"
  },
  {
    "round": 3,
    "phase": 1,
    "table": 9,
    "winner": "darkus96",
    "player1": "darkus96",
    "player2": "killbo"
  },
  {
    "round": 3,
    "phase": 1,
    "table": 10,
    "winner": "khronistr",
    "player1": "khronistr",
    "player2": "gato_333"
  },
  {
    "round": 3,
    "phase": 1,
    "table": 11,
    "winner": "javiee333",
    "player1": "aetherbenny",
    "player2": "javiee333"
  },
  {
    "round": 3,
    "phase": 1,
    "table": 12,
    "winner": "jrab",
    "player1": "wall456",
    "player2": "jrab"
  },
  {
    "round": 3,
    "phase": 1,
    "table": 13,
    "winner": "shinra67",
    "player1": "konono",
    "player2": "shinra67"
  },
  {
    "round": 3,
    "phase": 1,
    "table": 14,
    "winner": "fulcrumguy",
    "player1": "fulcrumguy",
    "player2": "manutan"
  },
  {
    "round": 3,
    "phase": 1,
    "table": 15,
    "winner": "mo0nwa1k3r",
    "player1": "mo0nwa1k3r",
    "player2": "sas"
  },
  {
    "round": 3,
    "phase": 1,
    "table": 16,
    "winner": "alhag114",
    "player1": "sheedy",
    "player2": "alhag114"
  },
  {
    "round": 3,
    "phase": 1,
    "table": 17,
    "winner": "acebakun",
    "player1": "dracoz",
    "player2": "acebakun"
  },
  {
    "round": 3,
    "phase": 1,
    "table": 18,
    "winner": "akfirestorm",
    "player1": "yaboishaad",
    "player2": "akfirestorm"
  },
  {
    "round": 3,
    "phase": 1,
    "table": 19,
    "winner": "russ_ii",
    "player1": "abbeie00",
    "player2": "russ_ii"
  },
  {
    "round": 3,
    "phase": 1,
    "table": 20,
    "winner": "joshuasutherland21",
    "player1": "ansito",
    "player2": "joshuasutherland21"
  },
  {
    "round": 3,
    "phase": 1,
    "table": 21,
    "winner": "stachyv2",
    "player1": "stachyv2",
    "player2": "elliedark"
  },
  {
    "round": 3,
    "phase": 1,
    "table": 22,
    "winner": "themagikarp",
    "player1": "r2rjp1",
    "player2": "themagikarp"
  },
  {
    "round": 3,
    "phase": 1,
    "table": 23,
    "winner": "tobias_oak",
    "player1": "tobias_oak",
    "player2": "kiddoz"
  },
  {
    "round": 3,
    "phase": 1,
    "table": 24,
    "winner": "hiii1",
    "player1": "hallow",
    "player2": "hiii1"
  },
  {
    "round": 3,
    "phase": 1,
    "table": 25,
    "winner": -1,
    "player1": "luxmea",
    "player2": "flipinton"
  },
  {
    "round": 3,
    "phase": 1,
    "table": 26,
    "winner": "oddmami",
    "player1": "oddmami",
    "player2": "flipand11"
  },
  {
    "round": 3,
    "phase": 1,
    "table": 27,
    "winner": "arackz85",
    "player1": "arackz85",
    "player2": "thay195"
  },
  {
    "round": 3,
    "phase": 1,
    "table": 28,
    "winner": "kraby29",
    "player1": "kraby29",
    "player2": "finpin"
  },
  {
    "round": 4,
    "phase": 1,
    "table": 1,
    "winner": "r0zey",
    "player1": "r0zey",
    "player2": "2sick"
  },
  {
    "round": 4,
    "phase": 1,
    "table": 2,
    "winner": "proskiftw",
    "player1": "my",
    "player2": "proskiftw"
  },
  {
    "round": 4,
    "phase": 1,
    "table": 3,
    "winner": "noobslybot_01",
    "player1": "awbscene",
    "player2": "noobslybot_01"
  },
  {
    "round": 4,
    "phase": 1,
    "table": 4,
    "winner": "disposablehero",
    "player1": "disposablehero",
    "player2": "piutonium"
  },
  {
    "round": 4,
    "phase": 1,
    "table": 5,
    "winner": "tommyhp",
    "player1": "tommyhp",
    "player2": "alhag114"
  },
  {
    "round": 4,
    "phase": 1,
    "table": 6,
    "winner": "russ_ii",
    "player1": "shinra67",
    "player2": "russ_ii"
  },
  {
    "round": 4,
    "phase": 1,
    "table": 7,
    "winner": "ruzlv",
    "player1": "javiee333",
    "player2": "ruzlv"
  },
  {
    "round": 4,
    "phase": 1,
    "table": 8,
    "winner": "khronistr",
    "player1": "mrd",
    "player2": "khronistr"
  },
  {
    "round": 4,
    "phase": 1,
    "table": 9,
    "winner": "skl_yizzy",
    "player1": "darkus96",
    "player2": "skl_yizzy"
  },
  {
    "round": 4,
    "phase": 1,
    "table": 10,
    "winner": "cyrunix",
    "player1": "rossytribiani",
    "player2": "cyrunix"
  },
  {
    "round": 4,
    "phase": 1,
    "table": 11,
    "winner": "tobias_oak",
    "player1": "stachyv2",
    "player2": "tobias_oak"
  },
  {
    "round": 4,
    "phase": 1,
    "table": 12,
    "winner": "rno",
    "player1": "akfirestorm",
    "player2": "rno"
  },
  {
    "round": 4,
    "phase": 1,
    "table": 13,
    "winner": "mo0nwa1k3r",
    "player1": "themagikarp",
    "player2": "mo0nwa1k3r"
  },
  {
    "round": 4,
    "phase": 1,
    "table": 14,
    "winner": "jrab",
    "player1": "fulcrumguy",
    "player2": "jrab"
  },
  {
    "round": 4,
    "phase": 1,
    "table": 15,
    "winner": "joshuasutherland21",
    "player1": "kakashi93",
    "player2": "joshuasutherland21"
  },
  {
    "round": 4,
    "phase": 1,
    "table": 16,
    "winner": "acebakun",
    "player1": "acebakun",
    "player2": "sheedy"
  },
  {
    "round": 4,
    "phase": 1,
    "table": 17,
    "winner": "manutan",
    "player1": "manutan",
    "player2": "oddmami"
  },
  {
    "round": 4,
    "phase": 1,
    "table": 18,
    "winner": "elliedark",
    "player1": "elliedark",
    "player2": "abbeie00"
  },
  {
    "round": 4,
    "phase": 1,
    "table": 19,
    "winner": "aetherbenny",
    "player1": "dracoz",
    "player2": "aetherbenny"
  },
  {
    "round": 4,
    "phase": 1,
    "table": 20,
    "winner": "ansito",
    "player1": "wall456",
    "player2": "ansito"
  },
  {
    "round": 4,
    "phase": 1,
    "table": 21,
    "winner": "konono",
    "player1": "killbo",
    "player2": "konono"
  },
  {
    "round": 4,
    "phase": 1,
    "table": 22,
    "winner": "r2rjp1",
    "player1": "r2rjp1",
    "player2": "arackz85"
  },
  {
    "round": 4,
    "phase": 1,
    "table": 23,
    "winner": "kraby29",
    "player1": "hiii1",
    "player2": "kraby29"
  },
  {
    "round": 4,
    "phase": 1,
    "table": 24,
    "winner": -1,
    "player1": "thay195",
    "player2": "hallow"
  },
  {
    "round": 4,
    "phase": 1,
    "table": 25,
    "winner": -1,
    "player1": "kiddoz",
    "player2": "finpin"
  },
  {
    "round": 4,
    "phase": 1,
    "table": 26,
    "winner": "flipinton",
    "player1": "flipinton"
  },
  {
    "round": 5,
    "phase": 1,
    "table": 1,
    "winner": "proskiftw",
    "player1": "proskiftw",
    "player2": "r0zey"
  },
  {
    "round": 5,
    "phase": 1,
    "table": 2,
    "winner": "noobslybot_01",
    "player1": "noobslybot_01",
    "player2": "disposablehero"
  },
  {
    "round": 5,
    "phase": 1,
    "table": 3,
    "winner": "2sick",
    "player1": "2sick",
    "player2": "mo0nwa1k3r"
  },
  {
    "round": 5,
    "phase": 1,
    "table": 4,
    "winner": "skl_yizzy",
    "player1": "skl_yizzy",
    "player2": "my"
  },
  {
    "round": 5,
    "phase": 1,
    "table": 5,
    "winner": "russ_ii",
    "player1": "tommyhp",
    "player2": "russ_ii"
  },
  {
    "round": 5,
    "phase": 1,
    "table": 6,
    "winner": "khronistr",
    "player1": "khronistr",
    "player2": "awbscene"
  },
  {
    "round": 5,
    "phase": 1,
    "table": 7,
    "winner": "rno",
    "player1": "rno",
    "player2": "joshuasutherland21"
  },
  {
    "round": 5,
    "phase": 1,
    "table": 8,
    "winner": "jrab",
    "player1": "jrab",
    "player2": "ruzlv"
  },
  {
    "round": 5,
    "phase": 1,
    "table": 9,
    "winner": "piutonium",
    "player1": "tobias_oak",
    "player2": "piutonium"
  },
  {
    "round": 5,
    "phase": 1,
    "table": 10,
    "winner": "cyrunix",
    "player1": "cyrunix",
    "player2": "acebakun"
  },
  {
    "round": 5,
    "phase": 1,
    "table": 11,
    "winner": "themagikarp",
    "player1": "themagikarp",
    "player2": "elliedark"
  },
  {
    "round": 5,
    "phase": 1,
    "table": 12,
    "winner": "konono",
    "player1": "r2rjp1",
    "player2": "konono"
  },
  {
    "round": 5,
    "phase": 1,
    "table": 13,
    "winner": "javiee333",
    "player1": "javiee333",
    "player2": "rossytribiani"
  },
  {
    "round": 5,
    "phase": 1,
    "table": 14,
    "winner": "darkus96",
    "player1": "fulcrumguy",
    "player2": "darkus96"
  },
  {
    "round": 5,
    "phase": 1,
    "table": 15,
    "winner": "kraby29",
    "player1": "shinra67",
    "player2": "kraby29"
  },
  {
    "round": 5,
    "phase": 1,
    "table": 16,
    "winner": "ansito",
    "player1": "ansito",
    "player2": "stachyv2"
  },
  {
    "round": 5,
    "phase": 1,
    "table": 17,
    "winner": "akfirestorm",
    "player1": "mrd",
    "player2": "akfirestorm"
  },
  {
    "round": 5,
    "phase": 1,
    "table": 18,
    "winner": "manutan",
    "player1": "manutan",
    "player2": "aetherbenny"
  },
  {
    "round": 5,
    "phase": 1,
    "table": 19,
    "winner": "killbo",
    "player1": "killbo",
    "player2": "flipinton"
  },
  {
    "round": 5,
    "phase": 1,
    "table": 20,
    "winner": -1,
    "player1": "dracoz",
    "player2": "abbeie00"
  },
  {
    "round": 5,
    "phase": 1,
    "table": 21,
    "winner": "oddmami",
    "player1": "arackz85",
    "player2": "oddmami"
  },
  {
    "round": 5,
    "phase": 1,
    "table": 22,
    "winner": -1,
    "player1": "kiddoz",
    "player2": "thay195"
  },
  {
    "round": 5,
    "phase": 1,
    "table": 23,
    "winner": -1,
    "player1": "hallow",
    "player2": "finpin"
  },
  {
    "round": 6,
    "phase": 1,
    "table": 1,
    "winner": "noobslybot_01",
    "player1": "proskiftw",
    "player2": "noobslybot_01"
  },
  {
    "round": 6,
    "phase": 1,
    "table": 2,
    "winner": "russ_ii",
    "player1": "skl_yizzy",
    "player2": "russ_ii"
  },
  {
    "round": 6,
    "phase": 1,
    "table": 3,
    "winner": "disposablehero",
    "player1": "disposablehero",
    "player2": "r0zey"
  },
  {
    "round": 6,
    "phase": 1,
    "table": 4,
    "winner": "rno",
    "player1": "rno",
    "player2": "jrab"
  },
  {
    "round": 6,
    "phase": 1,
    "table": 5,
    "winner": "piutonium",
    "player1": "khronistr",
    "player2": "piutonium"
  },
  {
    "round": 6,
    "phase": 1,
    "table": 6,
    "winner": "cyrunix",
    "player1": "2sick",
    "player2": "cyrunix"
  },
  {
    "round": 6,
    "phase": 1,
    "table": 7,
    "winner": "tobias_oak",
    "player1": "tobias_oak",
    "player2": "manutan"
  },
  {
    "round": 6,
    "phase": 1,
    "table": 8,
    "winner": "my",
    "player1": "acebakun",
    "player2": "my"
  },
  {
    "round": 6,
    "phase": 1,
    "table": 9,
    "winner": "themagikarp",
    "player1": "themagikarp",
    "player2": "javiee333"
  },
  {
    "round": 6,
    "phase": 1,
    "table": 10,
    "winner": "kraby29",
    "player1": "awbscene",
    "player2": "kraby29"
  },
  {
    "round": 6,
    "phase": 1,
    "table": 11,
    "winner": "akfirestorm",
    "player1": "darkus96",
    "player2": "akfirestorm"
  },
  {
    "round": 6,
    "phase": 1,
    "table": 12,
    "winner": "joshuasutherland21",
    "player1": "joshuasutherland21",
    "player2": "mo0nwa1k3r"
  },
  {
    "round": 6,
    "phase": 1,
    "table": 13,
    "winner": "ruzlv",
    "player1": "ruzlv",
    "player2": "tommyhp"
  },
  {
    "round": 6,
    "phase": 1,
    "table": 14,
    "winner": "konono",
    "player1": "ansito",
    "player2": "konono"
  },
  {
    "round": 6,
    "phase": 1,
    "table": 15,
    "winner": "killbo",
    "player1": "killbo",
    "player2": "shinra67"
  },
  {
    "round": 6,
    "phase": 1,
    "table": 16,
    "winner": "r2rjp1",
    "player1": "r2rjp1",
    "player2": "oddmami"
  },
  {
    "round": 6,
    "phase": 1,
    "table": 17,
    "winner": -1,
    "player1": "mrd",
    "player2": "stachyv2"
  },
  {
    "round": 6,
    "phase": 1,
    "table": 18,
    "winner": -1,
    "player1": "abbeie00",
    "player2": "flipinton"
  },
  {
    "round": 6,
    "phase": 1,
    "table": 19,
    "winner": -1,
    "player1": "dracoz",
    "player2": "thay195"
  },
  {
    "round": 6,
    "phase": 1,
    "table": 20,
    "winner": -1,
    "player1": "arackz85",
    "player2": "finpin"
  },
  {
    "round": 6,
    "phase": 1,
    "table": 21,
    "winner": -1,
    "player1": "hallow",
    "player2": "kiddoz"
  },
  {
    "round": 7,
    "phase": 1,
    "table": 1,
    "winner": 0,
    "player1": "noobslybot_01",
    "player2": "piutonium"
  },
  {
    "round": 7,
    "phase": 1,
    "table": 2,
    "winner": "proskiftw",
    "player1": "proskiftw",
    "player2": "cyrunix"
  },
  {
    "round": 7,
    "phase": 1,
    "table": 3,
    "winner": 0,
    "player1": "rno",
    "player2": "russ_ii"
  },
  {
    "round": 7,
    "phase": 1,
    "table": 4,
    "winner": "my",
    "player1": "disposablehero",
    "player2": "my"
  },
  {
    "round": 7,
    "phase": 1,
    "table": 5,
    "winner": "tobias_oak",
    "player1": "jrab",
    "player2": "tobias_oak"
  },
  {
    "round": 7,
    "phase": 1,
    "table": 6,
    "winner": "r0zey",
    "player1": "joshuasutherland21",
    "player2": "r0zey"
  },
  {
    "round": 7,
    "phase": 1,
    "table": 7,
    "winner": "themagikarp",
    "player1": "akfirestorm",
    "player2": "themagikarp"
  },
  {
    "round": 7,
    "phase": 1,
    "table": 8,
    "winner": "ruzlv",
    "player1": "skl_yizzy",
    "player2": "ruzlv"
  },
  {
    "round": 7,
    "phase": 1,
    "table": 9,
    "winner": "konono",
    "player1": "konono",
    "player2": "kraby29"
  },
  {
    "round": 7,
    "phase": 1,
    "table": 10,
    "winner": "2sick",
    "player1": "2sick",
    "player2": "khronistr"
  },
  {
    "round": 7,
    "phase": 1,
    "table": 11,
    "winner": "javiee333",
    "player1": "killbo",
    "player2": "javiee333"
  },
  {
    "round": 7,
    "phase": 1,
    "table": 12,
    "winner": "darkus96",
    "player1": "r2rjp1",
    "player2": "darkus96"
  },
  {
    "round": 7,
    "phase": 1,
    "table": 13,
    "winner": "ansito",
    "player1": "ansito",
    "player2": "mrd"
  },
  {
    "round": 7,
    "phase": 1,
    "table": 14,
    "winner": -1,
    "player1": "stachyv2",
    "player2": "oddmami"
  },
  {
    "round": 7,
    "phase": 1,
    "table": 15,
    "winner": -1,
    "player1": "abbeie00",
    "player2": "arackz85"
  },
  {
    "round": 7,
    "phase": 1,
    "table": 16,
    "winner": -1,
    "player1": "dracoz",
    "player2": "kiddoz"
  },
  {
    "round": 7,
    "phase": 1,
    "table": 17,
    "winner": -1,
    "player1": "flipinton",
    "player2": "hallow"
  },
  {
    "round": 7,
    "phase": 1,
    "table": 18,
    "winner": -1,
    "player1": "finpin",
    "player2": "thay195"
  },
  {
    "phase": 2,
    "round": 8,
    "winner": "cyrunix",
    "match": "T4-1",
    "player1": "cyrunix",
    "player2": "rno"
  },
  {
    "phase": 2,
    "round": 8,
    "winner": "my",
    "match": "T4-2",
    "player1": "proskiftw",
    "player2": "my"
  },
  {
    "phase": 2,
    "round": 8,
    "winner": "2sick",
    "match": "T16-6",
    "player1": "r0zey",
    "player2": "2sick"
  },
  {
    "phase": 2,
    "round": 8,
    "winner": "proskiftw",
    "match": "T8-3",
    "player1": "proskiftw",
    "player2": "2sick"
  },
  {
    "phase": 2,
    "round": 8,
    "winner": "russ_ii",
    "match": "T16-4",
    "player1": "russ_ii",
    "player2": "themagikarp"
  },
  {
    "phase": 2,
    "round": 8,
    "winner": "proskiftw",
    "match": "T16-5",
    "player1": "proskiftw"
  },
  {
    "phase": 2,
    "round": 8,
    "winner": "my",
    "match": "T8-4",
    "player1": "piutonium",
    "player2": "my"
  },
  {
    "phase": 2,
    "round": 8,
    "winner": "piutonium",
    "match": "T16-7",
    "player1": "piutonium",
    "player2": "konono"
  },
  {
    "phase": 2,
    "round": 8,
    "winner": "my",
    "match": "T2-1",
    "player1": "cyrunix",
    "player2": "my"
  },
  {
    "phase": 2,
    "round": 8,
    "winner": "cyrunix",
    "match": "T8-1",
    "player1": "noobslybot_01",
    "player2": "cyrunix"
  },
  {
    "phase": 2,
    "round": 8,
    "winner": "cyrunix",
    "match": "T16-2",
    "player1": "disposablehero",
    "player2": "cyrunix"
  },
  {
    "phase": 2,
    "round": 8,
    "winner": "rno",
    "match": "T16-3",
    "player1": "rno",
    "player2": "tobias_oak"
  },
  {
    "phase": 2,
    "round": 8,
    "winner": "rno",
    "match": "T8-2",
    "player1": "rno",
    "player2": "russ_ii"
  },
  {
    "phase": 2,
    "round": 8,
    "winner": "noobslybot_01",
    "match": "T16-1",
    "player1": "noobslybot_01"
  },
  {
    "phase": 2,
    "round": 8,
    "winner": "my",
    "match": "T16-8",
    "player1": "my",
    "player2": "ruzlv"
  }
]